{"1": "샌프란시스코", "2": "연합뉴스", "3": "정성호", "4": "특파원", "5": "가상", "6": "화폐", "7": "대장", "8": "격인", "9": "비트코인", "10": "가격", "11": "가까이", "12": "하락", "13": "등", "14": "급락", "15": "세", "16": "암호", "17": "정보", "18": "사이트", "19": "코인", "20": "데스크", "21": "미국", "22": "서부", "23": "시간", "24": "오전", "25": "한국", "26": "기준", "27": "전과", "28": "견줘", "29": "집계", "30": "약", "31": "달", "32": "전인", "33": "지난달", "34": "중순", "35": "것", "36": "비교", "37": "반", "38": "토막", "39": "이", "40": "웃", "41": "시가총액", "42": "론", "43": "머스크", "44": "테슬라", "45": "최고경영자", "46": "새벽", "47": "지지", "48": "취지", "49": "발언", "50": "트위터", "51": "뒤", "52": "돌기", "53": "약효", "54": "가지", "55": "은", "56": "전", "57": "다음", "58": "규모", "59": "더", "60": "리움", "61": "전보", "62": "거래", "63": "총", "64": "감소", "65": "적극", "66": "밀고", "67": "도지", "68": "역시", "69": "올해", "70": "급상승", "71": "장", "72": "연출", "73": "시장", "74": "지난", "75": "종전", "76": "입장", "77": "차량", "78": "구매", "79": "때", "80": "결제", "81": "수단", "82": "폭탄", "83": "선언", "84": "추락", "85": "이상", "86": "차지", "87": "나", "88": "수직", "89": "전체", "90": "증발", "91": "불과", "92": "주일", "93": "전만", "94": "해도", "95": "중국", "96": "금융", "97": "당국", "98": "민간", "99": "불허", "100": "방침", "101": "재천", "102": "부채질", "103": "풀이", "104": "은행업", "105": "협회", "106": "인터넷", "107": "지불", "108": "청산", "109": "기관", "110": "공동", "111": "발표", "112": "및", "113": "투기", "114": "위험", "115": "관", "116": "공고", "117": "를", "118": "통해", "119": "현상", "120": "강조", "121": "사용", "122": "거듭", "123": "규제", "124": "가세", "125": "재무부", "126": "가상화", "127": "폐가", "128": "조세", "129": "회피", "130": "불법행위", "131": "이용", "132": "수", "133": "기업", "134": "반드시", "135": "국세청", "136": "신고", "137": "국무원", "138": "안정", "139": "발전", "140": "위원회", "141": "류허", "142": "부총리", "143": "주재", "144": "회의", "145": "시스템", "146": "보호", "147": "위해", "148": "단속", "149": "채굴", "150": "타격", "151": "고", "152": "종류", "153": "변동성", "154": "점점", "155": "주류", "156": "편입", "157": "그", "158": "투자자", "159": "로부터", "160": "시선", "161": "끌", "162": "지적", "163": "사형", "164": "흑인", "165": "남성", "166": "무죄", "167": "입증", "168": "증거", "169": "논란", "170": "일", "171": "현지", "172": "레딜", "173": "리", "174": "사망", "175": "당시", "176": "이웃", "177": "여성", "178": "데브", "179": "리즈", "180": "살해", "181": "혐의", "182": "유죄", "183": "판결", "184": "재판", "185": "시작", "186": "직전", "187": "줄곧", "188": "주장", "189": "인정", "190": "집행", "191": "반전", "192": "유족", "193": "변호인", "194": "범행", "195": "흉기", "196": "다른", "197": "발견", "198": "사실", "199": "공개", "200": "변호", "201": "만약", "202": "결과", "203": "살인", "204": "흰색", "205": "셔츠", "206": "또한", "207": "범죄", "208": "현장", "209": "개", "210": "머리카락", "211": "대해", "212": "검사", "213": "실시", "214": "가운데", "215": "리가", "216": "용의", "217": "선상", "218": "직접", "219": "관련", "220": "물리", "221": "데", "222": "최근", "223": "인터뷰", "224": "사건", "225": "절대", "226": "거나", "227": "결정", "228": "말", "229": "다만", "230": "등장", "231": "의", "232": "주인", "233": "못", "234": "상태", "235": "국가", "236": "데이터베이스", "237": "입력", "238": "일치", "239": "사람", "240": "아칸소주", "241": "용", "242": "약물", "243": "공급", "244": "계약", "245": "종료", "246": "일이", "247": "이유", "248": "제기", "249": "각", "250": "주정", "251": "부가", "252": "졸람", "253": "고통", "254": "치", "255": "사약", "256": "투입", "257": "사형수", "258": "의식", "259": "기능", "260": "주사", "261": "방식", "262": "채택", "263": "기한", "264": "대규모", "265": "바", "266": "한편", "267": "영국", "268": "회", "269": "마지막", "270": "몇", "271": "마디", "272": "내", "273": "지금", "274": "늘", "275": "결백", "276": "이주연", "277": "인턴", "278": "기자", "279": "아시아", "280": "경제", "281": "김소영", "282": "국민", "283": "힘", "284": "대권", "285": "주자", "286": "원희룡", "287": "지사", "288": "정부", "289": "역할", "290": "방기", "291": "며", "292": "제도", "293": "정비", "294": "일일이", "295": "문제", "296": "검색", "297": "불량", "298": "거래소", "299": "서울", "300": "여의도", "301": "정치", "302": "문화", "303": "플랫폼", "304": "하우스", "305": "블록", "306": "체인", "307": "특강", "308": "강연", "309": "자로", "310": "나선", "311": "원", "312": "러", "313": "절박", "314": "광풍", "315": "면서", "316": "규정", "317": "라며", "318": "활용", "319": "디지털", "320": "영토", "321": "소탕", "322": "듯", "323": "박멸", "324": "무슨", "325": "혁신", "326": "이야기", "327": "하나", "328": "실제", "329": "투자", "330": "손해", "331": "자신", "332": "일화", "333": "부처님", "334": "오신", "335": "날", "336": "어치", "337": "나흘", "338": "체험", "339": "앞", "340": "대한", "341": "발언권", "342": "페이스북", "343": "글", "344": "법안", "345": "정책", "346": "각종", "347": "피해", "348": "속출", "349": "문제점", "350": "무엇", "351": "확인", "352": "계좌", "353": "개설", "354": "클레이튼", "355": "썸씽", "356": "여러", "357": "분할", "358": "매수", "359": "뉴스데스크", "360": "앵커", "361": "코로나", "362": "소식", "363": "주말", "364": "건", "365": "수가", "366": "새", "367": "확", "368": "진자", "369": "하루", "370": "다시", "371": "명", "372": "대로", "373": "지역", "374": "집단", "375": "감염", "376": "계속", "377": "대구", "378": "유흥업소", "379": "이제", "380": "백", "381": "충남", "382": "아산", "383": "온천", "384": "일흔", "385": "곽동건", "386": "보도", "387": "리포트", "388": "호텔", "389": "지하", "390": "구미", "391": "울산", "392": "손님", "393": "방문", "394": "처음", "395": "확진", "396": "이후", "397": "사흘", "398": "수십", "399": "오늘", "400": "종업원", "401": "추가", "402": "누적", "403": "목욕탕", "404": "곳", "405": "학원", "406": "사회", "407": "모두", "408": "동안", "409": "여명", "410": "접촉", "411": "추세", "412": "중", "413": "발생", "414": "신규", "415": "아래", "416": "토요일", "417": "평일", "418": "절반", "419": "영향", "420": "전해철", "421": "중앙", "422": "방역", "423": "대책", "424": "본부", "425": "차장", "426": "종교시설", "427": "음식점", "428": "목욕", "429": "상공간", "430": "전국", "431": "뜻", "432": "재생산", "433": "지수", "434": "도", "435": "오히려", "436": "유행", "437": "확산", "438": "조짐", "439": "보이", "440": "내일", "441": "주간", "442": "연장", "443": "거리", "444": "두기", "445": "지자체", "446": "별", "447": "상황", "448": "수준", "449": "선제", "450": "조치", "451": "달라", "452": "당부", "453": "뉴스", "454": "곽", "455": "영상", "456": "취재", "457": "정우영", "458": "영상편집", "459": "이현선", "460": "여러분", "461": "제보", "462": "전화", "463": "이메일", "464": "카카오", "465": "톡", "466": "기사", "467": "원문", "468": "학", "469": "한강", "470": "공원", "471": "실종", "472": "채", "473": "손정민", "474": "경찰", "475": "친구", "476": "씨", "477": "조사", "478": "종합", "479": "서초", "480": "경찰서", "481": "전날", "482": "참고인", "483": "신분", "484": "진행", "485": "이번", "486": "번", "487": "앞서", "488": "상대로", "489": "최면", "490": "프로파일러", "491": "면담", "492": "언론", "493": "꽤", "494": "장시간", "495": "아버지", "496": "어머니", "497": "각각", "498": "번의", "499": "손씨", "500": "경위", "501": "폐쇄회", "502": "분석", "503": "토양", "504": "성분", "505": "수사", "506": "벌이", "507": "양말", "508": "흙", "509": "인근", "510": "잔디밭", "511": "육지", "512": "물", "513": "경계", "514": "강물", "515": "속", "516": "지점", "517": "수거", "518": "국립", "519": "과학", "520": "연구원", "521": "국과수", "522": "의뢰", "523": "당일", "524": "의류", "525": "요청", "526": "쯤", "527": "전망", "528": "입수", "529": "목격자", "530": "증언", "531": "신원", "532": "미상", "533": "가능성", "534": "배제", "535": "파악", "536": "작업", "537": "청", "538": "접수", "539": "현재", "540": "소재", "541": "안", "542": "남성은", "543": "신빙", "544": "장소", "545": "광화문", "546": "광장", "547": "조화", "548": "공사", "549": "조선", "550": "시대", "551": "육조", "552": "발굴", "553": "시민", "554": "최고", "555": "행정", "556": "기구", "557": "의정부", "558": "호", "559": "예", "560": "병", "561": "형", "562": "공조", "563": "업무", "564": "관장", "565": "관청", "566": "길", "567": "중인", "568": "세종로", "569": "신청", "570": "답사", "571": "해설", "572": "사", "573": "안내", "574": "군사", "575": "총괄", "576": "삼군부", "577": "감찰", "578": "사헌부", "579": "터", "580": "차례", "581": "편", "582": "위치", "583": "후기", "584": "배수로", "585": "일제강점기", "586": "전신주", "587": "나무", "588": "기둥", "589": "또", "590": "건축", "591": "시기", "592": "은색", "593": "노란색", "594": "달리", "595": "표시", "596": "건물", "597": "흔적", "598": "앞쪽", "599": "가늠", "600": "케", "601": "문지", "602": "문", "603": "자리", "604": "우물", "605": "우상", "606": "대학생", "607": "달이", "608": "의혹", "609": "해소", "610": "커녕", "611": "화제", "612": "돈벌이", "613": "유튜버", "614": "생기", "615": "가짜", "616": "처벌", "617": "검토", "618": "저희", "619": "뉴스룸", "620": "정리", "621": "양", "622": "먼저", "623": "제시", "624": "만취", "625": "반박", "626": "도현", "627": "내용", "628": "사진", "629": "귀가", "630": "가족", "631": "오기", "632": "모든", "633": "기억", "634": "손현", "635": "슬리퍼", "636": "펜스", "637": "단", "638": "심지어", "639": "손", "640": "간단", "641": "블랙아웃", "642": "고사하고", "643": "술", "644": "취한", "645": "기운", "646": "차", "647": "세운", "648": "우리", "649": "연락", "650": "온", "651": "게", "652": "바로", "653": "직진", "654": "준", "655": "거", "656": "취해", "657": "강가", "658": "근처", "659": "아들", "660": "모습", "661": "보이지", "662": "설명", "663": "거기", "664": "만", "665": "강", "666": "비탈", "667": "둘", "668": "약간", "669": "이동", "670": "부친", "671": "얘", "672": "해", "673": "대화", "674": "점", "675": "보아", "676": "걔", "677": "묘사", "678": "뭔가", "679": "소주", "680": "덜", "681": "취했", "682": "두", "683": "네", "684": "막걸리", "685": "대작", "686": "취할", "687": "가장", "688": "원인", "689": "알", "690": "화장", "691": "끝", "692": "부모", "693": "디자인", "694": "이창환", "695": "배", "696": "윤주", "697": "뉴시스", "698": "박주연", "699": "최태원", "700": "상공회의소", "701": "회장", "702": "정상회담", "703": "워싱턴", "704": "양국", "705": "재계", "706": "실질", "707": "협력", "708": "위", "709": "외교", "710": "상의", "711": "취임", "712": "첫", "713": "해외", "714": "일정", "715": "문재인", "716": "대통령", "717": "방미", "718": "사절단", "719": "참여", "720": "인사", "721": "경협", "722": "네트워크", "723": "최", "724": "단체", "725": "시각", "726": "한미", "727": "비즈니스", "728": "라운드", "729": "테이블", "730": "참석", "731": "반도체", "732": "배터리", "733": "바이오", "734": "산업", "735": "대미", "736": "확대", "737": "양질", "738": "일자리", "739": "환경보호", "740": "중심", "741": "가치", "742": "창", "743": "직후", "744": "지나", "745": "레이몬", "746": "상무부", "747": "장관", "748": "환담", "749": "현안", "750": "오후", "751": "백악관", "752": "브리핑", "753": "소화", "754": "후", "755": "임", "756": "감안", "757": "유력", "758": "싱크탱크", "759": "리더", "760": "경쟁력", "761": "방안", "762": "모색", "763": "주력", "764": "대표", "765": "조슈아", "766": "볼튼", "767": "폴", "768": "덜레이", "769": "통상", "770": "국제", "771": "담당", "772": "부회장", "773": "화상", "774": "논의", "775": "설립", "776": "애플", "777": "아마존", "778": "월마트", "779": "제너럴", "780": "모터", "781": "스", "782": "존슨앤존슨", "783": "대기업", "784": "구성", "785": "미제", "786": "조업", "787": "지속", "788": "성장", "789": "이해관계자", "790": "자본주의", "791": "환경", "792": "지배구조", "793": "경영", "794": "기업가", "795": "정신", "796": "기반", "797": "인식", "798": "공유", "799": "구체", "800": "실효", "801": "방법론", "802": "급변", "803": "정세", "804": "불확실", "805": "증대", "806": "기후변화", "807": "소득", "808": "격차", "809": "인구", "810": "직면", "811": "문제해결", "812": "정착", "813": "서로", "814": "제안", "815": "고객", "816": "근로자", "817": "존중", "818": "추구", "819": "궤", "820": "초청", "821": "감사", "822": "해결", "823": "노력", "824": "답", "825": "정보통", "826": "제이슨", "827": "옥스먼", "828": "롭", "829": "스트", "830": "레이어", "831": "바이든", "832": "행정부", "833": "재편", "834": "전략", "835": "통신", "836": "동향", "837": "의견", "838": "수렴", "839": "국내", "840": "강화", "841": "구글", "842": "마이크로소프트", "843": "인텔", "844": "하이닉스", "845": "삼성", "846": "전자", "847": "대만", "848": "세계", "849": "회원", "850": "가입", "851": "분야", "852": "그간", "853": "역", "854": "적", "855": "전기차", "856": "양산", "857": "파트너", "858": "단계", "859": "채널", "860": "구축", "861": "재건", "862": "글로벌", "863": "리더십", "864": "회복", "865": "관심", "866": "우호", "867": "더욱", "868": "증진", "869": "유명", "870": "애틀랜틱", "871": "카운슬", "872": "전문가", "873": "네트워킹", "874": "갈등", "875": "패러다임", "876": "과정", "877": "위기", "878": "대응", "879": "능력", "880": "기여", "881": "판단", "882": "강석", "883": "구", "884": "본부장", "885": "기간", "886": "최대한", "887": "계간", "888": "관계", "889": "활동", "890": "교역", "891": "차원", "892": "공감", "893": "동아일보", "894": "검", "895": "형사", "896": "부", "897": "부장", "898": "일찍", "899": "차관", "900": "택시", "901": "폭행", "902": "내사", "903": "종결", "904": "측은", "905": "변호사", "906": "입회", "907": "사법연수원", "908": "후배", "909": "행사", "910": "임명", "911": "지난해", "912": "초", "913": "서초구", "914": "아파트", "915": "단지", "916": "멱살", "917": "의사", "918": "불벌", "919": "죄인", "920": "형법", "921": "일반", "922": "적용", "923": "처리", "924": "운행", "925": "운전자", "926": "특정", "927": "가중", "928": "법", "929": "시민단체", "930": "고발", "931": "특가법", "932": "피해자", "933": "검찰", "934": "당초", "935": "목", "936": "분량", "937": "동영상", "938": "확보", "939": "압수수색", "940": "외압", "941": "만큼", "942": "기소", "943": "여부", "944": "예정", "945": "경우", "946": "유지", "947": "안팎", "948": "별도", "949": "경찰청", "950": "단장", "951": "진상", "952": "사단", "953": "부실", "954": "전반", "955": "황성호", "956": "박종민", "957": "아프리카", "958": "중부", "959": "콩고민주공화국", "960": "민주", "961": "콩고", "962": "화산", "963": "대폭발", "964": "주민", "965": "대피", "966": "지구", "967": "하나로", "968": "니", "969": "폭발", "970": "유럽", "971": "순방", "972": "펠릭스", "973": "치세케디", "974": "단축", "975": "조기", "976": "귀국", "977": "사태", "978": "수습", "979": "동부", "980": "비룽", "981": "국립공원", "982": "용암", "983": "북", "984": "키부", "985": "주", "986": "도시", "987": "베니", "988": "대도시", "989": "고마", "990": "교외", "991": "시티", "992": "공항", "993": "가장자리", "994": "도로", "995": "시내", "996": "전력", "997": "통화", "998": "연결", "999": "원활", "1000": "공황", "1001": "전역", "1002": "긴급", "1003": "령", "1004": "피난", "1005": "행렬", "1006": "기도", "1007": "피난민", "1008": "상당수", "1009": "국경", "1010": "나라", "1011": "르완다", "1012": "향", "1013": "도보", "1014": "학교", "1015": "임시", "1016": "주둔", "1017": "유엔평화유지군", "1018": "전투기", "1019": "남쪽", "1020": "부카부", "1021": "인접", "1022": "국", "1023": "우간다", "1024": "엔테베", "1025": "철수", "1026": "통제", "1027": "집", "1028": "진정", "1029": "화산폭발", "1030": "인명", "1031": "보고", "1032": "휠체어", "1033": "노병", "1034": "미군", "1035": "훈장", "1036": "명예", "1037": "려고", "1038": "다해", "1039": "스스로", "1040": "장교", "1041": "보행", "1042": "보조", "1043": "옆", "1044": "부축", "1045": "손길", "1046": "육군", "1047": "레인저", "1048": "특수", "1049": "부대", "1050": "중위", "1051": "중국군", "1052": "병력", "1053": "남자", "1054": "자존심", "1055": "용납", "1056": "정상", "1057": "수여", "1058": "랠프", "1059": "퍼킷", "1060": "주니어", "1061": "예비역", "1062": "대령", "1063": "서훈", "1064": "사유", "1065": "낭독", "1066": "도움", "1067": "거절", "1068": "홀로", "1069": "순간", "1070": "우레", "1071": "박수", "1072": "곁", "1073": "하이라이트", "1074": "전쟁", "1075": "청천강", "1076": "일대", "1077": "고지", "1078": "명과", "1079": "카투사", "1080": "중공군", "1081": "수백", "1082": "친", "1083": "공로", "1084": "부하", "1085": "적의", "1086": "참호", "1087": "밖", "1088": "부상", "1089": "지휘", "1090": "용기", "1091": "감동", "1092": "이등병", "1093": "가라", "1094": "명령", "1095": "불복", "1096": "덕분", "1097": "목숨", "1098": "존경", "1099": "표", "1100": "똑바로", "1101": "청력", "1102": "대신", "1103": "응", "1104": "아내", "1105": "진", "1106": "여사", "1107": "남편", "1108": "베트남전", "1109": "참전", "1110": "수훈", "1111": "십자", "1112": "은성", "1113": "동성", "1114": "평소", "1115": "공적", "1116": "거의", "1117": "오라", "1118": "왜", "1119": "야단", "1120": "이오", "1121": "그냥", "1122": "우편", "1123": "반응", "1124": "제", "1125": "군", "1126": "복무", "1127": "야단법석", "1128": "자격", "1129": "줄", "1130": "기회", "1131": "입버릇", "1132": "포화", "1133": "전장", "1134": "질문", "1135": "방어", "1136": "정말", "1137": "소명", "1138": "보람", "1139": "성공", "1140": "임무", "1141": "세월", "1142": "반문", "1143": "직장인", "1144": "이모", "1145": "요즘", "1146": "비", "1147": "자만", "1148": "나스닥", "1149": "상장", "1150": "베이스", "1151": "주식", "1152": "회사", "1153": "주가", "1154": "이씨", "1155": "평가", "1156": "손실", "1157": "후회", "1158": "막심", "1159": "촉발", "1160": "쇼크", "1161": "종목", "1162": "크게", "1163": "동학", "1164": "개미", "1165": "서학", "1166": "산", "1167": "증시", "1168": "분", "1169": "보유", "1170": "업", "1171": "비트", "1172": "운영", "1173": "코스닥", "1174": "에이", "1175": "티", "1176": "베스트", "1177": "이틀", "1178": "기술", "1179": "분율", "1180": "한화", "1181": "증권", "1182": "사인", "1183": "덴트", "1184": "빗썸", "1185": "코리아", "1186": "최저", "1187": "기록", "1188": "업체", "1189": "라이엇", "1190": "달러", "1191": "소프트웨어", "1192": "마이크", "1193": "로스트", "1194": "가량", "1195": "탁", "1196": "잔고", "1197": "편득현", "1198": "부부", "1199": "일부", "1200": "거품", "1201": "익명", "1202": "원한", "1203": "자산운용", "1204": "임원", "1205": "각국", "1206": "주도", "1207": "충격", "1208": "대형", "1209": "코빗", "1210": "제외", "1211": "중소", "1212": "무더기", "1213": "폐쇄될", "1214": "은행", "1215": "실명", "1216": "제휴", "1217": "영업", "1218": "농협", "1219": "케이", "1220": "뱅크", "1221": "코", "1222": "신한은행", "1223": "시중", "1224": "우리은행", "1225": "쪽", "1226": "정", "1227": "신한", "1228": "기존", "1229": "난색", "1230": "지방", "1231": "외국", "1232": "대상", "1233": "특금법", "1234": "정보보호", "1235": "관리", "1236": "체계", "1237": "인증", "1238": "입출금", "1239": "계정", "1240": "요건", "1241": "금융정보분석원", "1242": "검증", "1243": "착수", "1244": "자칫", "1245": "사고", "1246": "책임", "1247": "부담", "1248": "우리금융", "1249": "그룹", "1250": "관계자", "1251": "수수료", "1252": "수익", "1253": "자금세탁", "1254": "해킹", "1255": "연루", "1256": "매우", "1257": "절차", "1258": "보완", "1259": "재계약", "1260": "발급", "1261": "업계", "1262": "자릿수", "1263": "여", "1264": "금융위", "1265": "심의회", "1266": "비판", "1267": "금발", "1268": "심", "1269": "분과", "1270": "위원장", "1271": "워크숍", "1272": "개최", "1273": "김용진", "1274": "서강대", "1275": "학부", "1276": "교수", "1277": "규율", "1278": "그동안", "1279": "상품", "1280": "볼", "1281": "때문", "1282": "소관", "1283": "부처", "1284": "황", "1285": "영", "1286": "효성", "1287": "조소영", "1288": "북한", "1289": "국적", "1290": "화물선", "1291": "동해", "1292": "침몰", "1293": "타고", "1294": "승조", "1295": "전원", "1296": "구조", "1297": "일본", "1298": "외신", "1299": "톤", "1300": "청봉", "1301": "호가", "1302": "해상보안청", "1303": "관구", "1304": "해상", "1305": "보안", "1306": "청봉호", "1307": "화물", "1308": "창고", "1309": "침수", "1310": "선원", "1311": "구명정", "1312": "탈출", "1313": "유조선", "1314": "항구", "1315": "자국", "1316": "철", "1317": "운반", "1318": "해역", "1319": "기름", "1320": "유출", "1321": "적하", "1322": "서도", "1323": "일각", "1324": "해당", "1325": "선박", "1326": "유엔", "1327": "안전보장", "1328": "이사회", "1329": "안보리", "1330": "제재", "1331": "대북", "1332": "피하", "1333": "추측", "1334": "조", "1335": "단독", "1336": "회담", "1337": "메릴랜드주", "1338": "크랩", "1339": "케이크", "1340": "메뉴", "1341": "오찬", "1342": "히데", "1343": "총리와", "1344": "햄버거", "1345": "식사", "1346": "정만호", "1347": "청와대", "1348": "소통", "1349": "수석", "1350": "해산물", "1351": "식성", "1352": "고려", "1353": "메릴랜드", "1354": "메인", "1355": "준비", "1356": "측", "1357": "격식", "1358": "만찬", "1359": "요구", "1360": "마스크", "1361": "국전", "1362": "참석자", "1363": "질병", "1364": "예방", "1365": "센터", "1366": "백신", "1367": "접종", "1368": "실내", "1369": "악수", "1370": "이어진", "1371": "기자회견", "1372": "호명", "1373": "자단", "1374": "잠깐", "1375": "정적", "1376": "의미", "1377": "생각", "1378": "성과", "1379": "간", "1380": "포괄", "1381": "합의", "1382": "총리", "1383": "실수", "1384": "연설", "1385": "말미", "1386": "종종", "1387": "잊힌", "1388": "여기", "1389": "증명", "1390": "언급", "1391": "단어", "1392": "방송", "1393": "뉴욕", "1394": "포스트", "1395": "결례", "1396": "범", "1397": "식이", "1398": "기념", "1399": "촬영", "1400": "양옆", "1401": "한쪽", "1402": "무릎", "1403": "위암", "1404": "기", "1405": "진단", "1406": "난생처음", "1407": "위로", "1408": "마음", "1409": "불신", "1410": "원망", "1411": "사업", "1412": "가정", "1413": "청소", "1414": "일과", "1415": "식당", "1416": "궂", "1417": "저", "1418": "시절", "1419": "내내", "1420": "빈", "1421": "희생", "1422": "움", "1423": "란", "1424": "고민", "1425": "부모님", "1426": "외도", "1427": "여자", "1428": "상대", "1429": "두둔", "1430": "목소리", "1431": "평생", "1432": "그때", "1433": "신뢰", "1434": "한번", "1435": "부부싸움", "1436": "화가", "1437": "난", "1438": "주방", "1439": "칼", "1440": "찾기", "1441": "놀란", "1442": "이내", "1443": "공포", "1444": "일주일", "1445": "번만", "1446": "저녁", "1447": "대학", "1448": "졸업", "1449": "행동", "1450": "척", "1451": "나니", "1452": "사랑", "1453": "거짓", "1454": "의심", "1455": "정서", "1456": "부재", "1457": "한평생", "1458": "얘기", "1459": "감정", "1460": "쓰레기통", "1461": "부정", "1462": "인생", "1463": "부채", "1464": "갑자기", "1465": "암", "1466": "심정은", "1467": "염려", "1468": "건강검진", "1469": "고생", "1470": "수발", "1471": "기적", "1472": "남아", "1473": "온갖", "1474": "항", "1475": "암치료", "1476": "중단", "1477": "시골", "1478": "자연", "1479": "치료", "1480": "가출", "1481": "사과", "1482": "화해", "1483": "용서", "1484": "마음대로", "1485": "슬픔", "1486": "안도", "1487": "감", "1488": "요", "1489": "김지선", "1490": "가명", "1491": "회사원", "1492": "지선", "1493": "당신", "1494": "사연", "1495": "우선", "1496": "외", "1497": "심정", "1498": "아주", "1499": "멀리", "1500": "돈", "1501": "다기", "1502": "신경", "1503": "부양", "1504": "자기", "1505": "사람인", "1506": "자식", "1507": "부분", "1508": "대답", "1509": "삶", "1510": "얼마나", "1511": "끝내", "1512": "좌절", "1513": "자녀", "1514": "생계", "1515": "이혼", "1516": "참고", "1517": "분노", "1518": "여지", "1519": "상처", "1520": "머리", "1521": "얼마", "1522": "남지", "1523": "걸", "1524": "기본", "1525": "형태", "1526": "마치", "1527": "선물", "1528": "상자", "1529": "껍데기", "1530": "포장", "1531": "처럼", "1532": "땐", "1533": "처", "1534": "조금", "1535": "외면", "1536": "재현", "1537": "건강", "1538": "누구", "1539": "생명", "1540": "순위", "1541": "에너지", "1542": "동원", "1543": "태도", "1544": "환자", "1545": "한시", "1546": "굳은살", "1547": "아픔", "1548": "상식", "1549": "보편", "1550": "이기", "1551": "도리", "1552": "내면", "1553": "면", "1554": "그게", "1555": "수도", "1556": "자존감", "1557": "생존", "1558": "인간", "1559": "자긍심", "1560": "확신", "1561": "대부분", "1562": "조건", "1563": "경험", "1564": "노고", "1565": "외로움", "1566": "녀", "1567": "이의", "1568": "무의식", "1569": "도덕", "1570": "종교", "1571": "이해", "1572": "거지", "1573": "자아", "1574": "막상", "1575": "현실", "1576": "죄책감", "1577": "깊이", "1578": "잘못", "1579": "걸음", "1580": "느낌", "1581": "어서", "1582": "특성", "1583": "아마", "1584": "결혼", "1585": "아이", "1586": "꼭", "1587": "원래", "1588": "누가", "1589": "설사", "1590": "일지", "1591": "훼손", "1592": "교과서", "1593": "좀", "1594": "객관", "1595": "살", "1596": "편지", "1597": "전달", "1598": "세상", "1599": "그것", "1600": "테", "1601": "내킨다", "1602": "하소연", "1603": "그르", "1604": "만하", "1605": "수용", "1606": "필요", "1607": "바란", "1608": "너", "1609": "성인", "1610": "나가야", "1611": "진실", "1612": "변치", "1613": "강지원", "1614": "상담", "1615": "신청서", "1616": "작성", "1617": "로", "1618": "선정", "1619": "일보", "1620": "소개", "1621": "내려받기", "1622": "이탈리아", "1623": "호수", "1624": "마조레", "1625": "케이블카", "1626": "최소", "1627": "마을", "1628": "중상", "1629": "구조대", "1630": "해발", "1631": "로이터", "1632": "인용", "1633": "탑승", "1634": "이중", "1635": "명의", "1636": "어린이", "1637": "헬리콥터", "1638": "북부", "1639": "토리노", "1640": "병원", "1641": "이송", "1642": "추정", "1643": "사항", "1644": "상단", "1645": "케이블", "1646": "것일", "1647": "옥", "1648": "장려", "1649": "지원", "1650": "금도", "1651": "허가", "1652": "퇴짜", "1653": "도면", "1654": "이현정", "1655": "박광남", "1656": "은평", "1657": "자주", "1658": "거래처", "1659": "정취", "1660": "층", "1661": "바닥", "1662": "서까래", "1663": "설계", "1664": "서울시", "1665": "심의", "1666": "통과", "1667": "창호", "1668": "담장이", "1669": "지붕", "1670": "높이", "1671": "과도", "1672": "주변", "1673": "놨습니", "1674": "반대", "1675": "조언", "1676": "시", "1677": "원금", "1678": "포기", "1679": "은평구", "1680": "거부", "1681": "위원", "1682": "충족", "1683": "이루", "1684": "정성", "1685": "답변", "1686": "대목장", "1687": "중요", "1688": "무형문화재", "1689": "재심", "1690": "의결", "1691": "전통", "1692": "편법", "1693": "원칙", "1694": "합리", "1695": "접목", "1696": "흐름", "1697": "박", "1698": "소송", "1699": "공장", "1700": "과연", "1701": "도시락", "1702": "말리", "1703": "이승환", "1704": "경", "1705": "윤태호", "1706": "경기도", "1707": "남양주시", "1708": "야산", "1709": "기슭", "1710": "견", "1711": "습격", "1712": "출동", "1713": "소방대", "1714": "나중", "1715": "유기견", "1716": "관측", "1717": "남양주", "1718": "진건읍", "1719": "능리", "1720": "지인", "1721": "혼자", "1722": "농장", "1723": "방범", "1724": "카메라", "1725": "행적", "1726": "장면", "1727": "봉변", "1728": "직원", "1729": "바깥", "1730": "피", "1731": "구급대원", "1732": "도착", "1733": "뒷덜미", "1734": "대원", "1735": "마취", "1736": "포획", "1737": "풍산개", "1738": "사모예드", "1739": "잡종", "1740": "몸", "1741": "길이", "1742": "몸무게", "1743": "정도", "1744": "외출", "1745": "목줄", "1746": "입", "1747": "마개", "1748": "안전", "1749": "장치", "1750": "맹견", "1751": "지정", "1752": "감식", "1753": "안락사", "1754": "손해배상", "1755": "마리", "1756": "사육", "1757": "전혀", "1758": "가끔", "1759": "먹이", "1760": "배회", "1761": "개월", "1762": "진술", "1763": "김영환", "1764": "국회의원", "1765": "한미정상회담", "1766": "혹평", "1767": "의원", "1768": "수고", "1769": "생색", "1770": "과", "1771": "변죽", "1772": "모순", "1773": "외화", "1774": "내빈", "1775": "강정", "1776": "여름", "1777": "찻집", "1778": "노랫말", "1779": "죄", "1780": "사이", "1781": "오락가락", "1782": "구럭", "1783": "김", "1784": "중국몽", "1785": "동맹국", "1786": "비핵화", "1787": "의지", "1788": "민족", "1789": "끼리", "1790": "관철", "1791": "대한민국", "1792": "만남", "1793": "앙금", "1794": "낼", "1795": "보아오", "1796": "포럼", "1797": "메시지", "1798": "의례", "1799": "일진", "1800": "일로", "1801": "칭송", "1802": "추", "1803": "안보", "1804": "문정인", "1805": "인권", "1806": "거론", "1807": "집권", "1808": "민주주의", "1809": "쓴소리", "1810": "탁현민", "1811": "인해전술", "1812": "랄프", "1813": "퍼켓", "1814": "명예훈장", "1815": "선택", "1816": "배치", "1817": "웅변", "1818": "화답", "1819": "흥남", "1820": "부두", "1821": "동맹", "1822": "아침", "1823": "잔", "1824": "차로", "1825": "복원", "1826": "철통", "1827": "혈맹", "1828": "눈물", "1829": "곡예", "1830": "별로", "1831": "평화", "1832": "오지", "1833": "북핵", "1834": "대륙", "1835": "탄도탄", "1836": "위협", "1837": "지라", "1838": "사정거리", "1839": "미사일", "1840": "싱가폴", "1841": "판문점", "1842": "김정은", "1843": "염불", "1844": "나위", "1845": "반영", "1846": "깜짝선물", "1847": "선진국", "1848": "형편", "1849": "내부", "1850": "만만", "1851": "중요성", "1852": "중시", "1853": "성김", "1854": "특별", "1855": "협상", "1856": "부연", "1857": "권준영", "1858": "월요일", "1859": "세대", "1860": "링링", "1861": "출생", "1862": "용어", "1863": "불굴", "1864": "중화", "1865": "혈통", "1866": "특징", "1867": "지금껏", "1868": "중국인", "1869": "공통", "1870": "목표", "1871": "진전", "1872": "공산당", "1873": "체제", "1874": "선전", "1875": "노래", "1876": "핫", "1877": "힙합", "1878": "뮤지션", "1879": "랩", "1880": "가사", "1881": "풍자", "1882": "저항", "1883": "음악인", "1884": "순치", "1885": "팟캐스트", "1886": "듣기", "1887": "인기", "1888": "아이돌", "1889": "갓세븐", "1890": "홍콩", "1891": "출신", "1892": "멤버", "1893": "왕", "1894": "잭슨", "1895": "홍", "1896": "이란", "1897": "팝", "1898": "가수", "1899": "어가", "1900": "마카오", "1901": "합법", "1902": "오직", "1903": "이념", "1904": "엑소", "1905": "레이", "1906": "모델", "1907": "광고", "1908": "별개", "1909": "해지", "1910": "반발", "1911": "대만해협", "1912": "명시", "1913": "비어", "1914": "쏙쏙", "1915": "흡수", "1916": "베이징올림픽", "1917": "유년", "1918": "관통", "1919": "사회주의", "1920": "사상", "1921": "맹목", "1922": "추종", "1923": "조국", "1924": "자부심", "1925": "충성", "1926": "하늘", "1927": "국뽕", "1928": "반감", "1929": "우리나라", "1930": "예상", "1931": "후원", "1932": "청년", "1933": "중심부", "1934": "조만간", "1935": "맞닥뜨릴", "1936": "미래", "1937": "생활", "1938": "조선일보", "1939": "밀레", "1940": "얼", "1941": "통인", "1942": "이벌찬", "1943": "구분", "1944": "심화", "1945": "무대", "1946": "꿀팁", "1947": "조목조목", "1948": "대체", "1949": "욕", "1950": "일단", "1951": "상치", "1952": "반중", "1953": "청취", "1954": "자", "1955": "환영", "1956": "앱", "1957": "홈페이지", "1958": "제공", "1959": "오디오", "1960": "팟빵", "1961": "아이튠즈", "1962": "보기", "1963": "링크", "1964": "조선닷컴", "1965": "작동", "1966": "주소", "1967": "중국어", "1968": "통", "1969": "클라스", "1970": "바링", "1971": "링", "1972": "래야", "1973": "금수", "1974": "푸얼", "1975": "챔피언", "1976": "청뚜", "1977": "나이트", "1978": "추억", "1979": "서방", "1980": "떼놈", "1981": "옛말", "1982": "키", "1983": "워드", "1984": "우투", "1985": "워", "1986": "밸", "1987": "꼰대", "1988": "감시", "1989": "뭐", "1990": "취업", "1991": "난민", "1992": "행복", "1993": "회로", "1994": "궈", "1995": "차오", "1996": "마케팅", "1997": "필수", "1998": "갑부", "1999": "만난", "2000": "상하이", "2001": "베이징", "2002": "앓이", "2003": "애국", "2004": "주의", "2005": "표현", "2006": "겨우", "2007": "서른", "2008": "김치", "2009": "한복", "2010": "칭찬", "2011": "청소년", "2012": "심근", "2013": "염", "2014": "연관", "2015": "중이", "2016": "뉴욕타임스", "2017": "초기", "2018": "전령", "2019": "화이자", "2020": "투여", "2021": "증상", "2022": "주로", "2023": "이상인", "2024": "연령", "2025": "의료", "2026": "불분명", "2027": "시립", "2028": "벨뷰", "2029": "감염병", "2030": "전문의", "2031": "젤린", "2032": "군더", "2033": "박사", "2034": "우연", "2035": "사례", "2036": "소아과", "2037": "학회", "2038": "이본", "2039": "말도나도", "2040": "스탠퍼드대", "2041": "인지", "2042": "자료", "2043": "매년", "2044": "명당", "2045": "피로", "2046": "흉통", "2047": "부정맥", "2048": "심장", "2049": "질환", "2050": "이스라엘", "2051": "보건", "2052": "영교", "2053": "초선", "2054": "김웅", "2055": "김은혜", "2056": "원외", "2057": "이준석", "2058": "선거", "2059": "후보", "2060": "등록", "2061": "토론회", "2062": "주호영", "2063": "나경원", "2064": "중진", "2065": "텃밭", "2066": "영남", "2067": "장파", "2068": "계", "2069": "파가", "2070": "유승민", "2071": "초반", "2072": "여론조사", "2073": "하자", "2074": "전이", "2075": "정권", "2076": "교체", "2077": "주제", "2078": "토론", "2079": "대선", "2080": "경선", "2081": "정병국", "2082": "유", "2083": "과거", "2084": "정당", "2085": "작년", "2086": "총선", "2087": "세력", "2088": "경북", "2089": "부산", "2090": "강원도", "2091": "윤석열", "2092": "외부", "2093": "국민의당", "2094": "합당", "2095": "마무리", "2096": "당원", "2097": "당", "2098": "쇄신", "2099": "책", "2100": "공천", "2101": "생중계", "2102": "공약", "2103": "한길", "2104": "리서치", "2105": "지지도", "2106": "순", "2107": "투표", "2108": "섣불리", "2109": "선", "2110": "인지도", "2111": "경쟁", "2112": "성격", "2113": "인기투표", "2114": "표방", "2115": "계보", "2116": "파주", "2117": "의적", "2118": "뿐", "2119": "김솔희", "2120": "미디어", "2121": "본질", "2122": "이재용", "2123": "사면", "2124": "플러스", "2125": "공공", "2126": "풀", "2127": "뿌리", "2128": "옥천신문", "2129": "커뮤니케이션", "2130": "안녕하십니까", "2131": "연우", "2132": "스튜디오", "2133": "출연", "2134": "셔", "2135": "맞춤", "2136": "어", "2137": "덩달아", "2138": "얼굴", "2139": "기대", "2140": "본격", "2141": "전방", "2142": "연일", "2143": "띄우기", "2144": "집중", "2145": "구속", "2146": "일련", "2147": "국정", "2148": "농단", "2149": "박근혜", "2150": "탄핵", "2151": "정경", "2152": "유착", "2153": "박영수", "2154": "특검", "2155": "서원", "2156": "뇌물", "2157": "최종", "2158": "특별검사", "2159": "실", "2160": "최지성", "2161": "공모", "2162": "승계", "2163": "목적", "2164": "자금", "2165": "횡령", "2166": "공", "2167": "징역", "2168": "선고", "2169": "다음해", "2170": "집행유예", "2171": "석방", "2172": "대법원", "2173": "체", "2174": "파기", "2175": "환송", "2176": "사과문", "2177": "세습", "2178": "고법", "2179": "법정", "2180": "청탁", "2181": "회삿돈", "2182": "대고", "2183": "은폐", "2184": "점도", "2185": "실형", "2186": "법원", "2187": "수감", "2188": "만기", "2189": "소일", "2190": "형기", "2191": "갈수록", "2192": "강도", "2193": "젠", "2194": "촉구", "2195": "도입", "2196": "특사", "2197": "여당", "2198": "민주당", "2199": "조차", "2200": "갑론", "2201": "주년", "2202": "권한", "2203": "결코", "2204": "사안", "2205": "광복절", "2206": "가석방", "2207": "불법", "2208": "막", "2209": "보시", "2210": "자본시장", "2211": "위반", "2212": "시세", "2213": "조종", "2214": "행위", "2215": "배임", "2216": "중형", "2217": "경향", "2218": "봇물", "2219": "보도국", "2220": "이용자", "2221": "팀", "2222": "네이버", "2223": "포털", "2224": "일간", "2225": "매체", "2226": "데이터", "2227": "포함", "2228": "송고된", "2229": "무려", "2230": "언론사", "2231": "랭킹", "2232": "겨", "2233": "상위", "2234": "머니투데이", "2235": "제지", "2236": "쓰기", "2237": "이재", "2238": "용비어천가", "2239": "세팅", "2240": "대중", "2241": "는걸", "2242": "사범", "2243": "듭니", "2244": "이슈", "2245": "언제", "2246": "보", "2247": "도량", "2248": "오규석", "2249": "기장군", "2250": "수의", "2251": "호소", "2252": "건의", "2253": "제출", "2254": "인물", "2255": "주목", "2256": "그대로", "2257": "복역", "2258": "불", "2259": "계기", "2260": "랄", "2261": "누군가", "2262": "명분", "2263": "손경", "2264": "그다음", "2265": "논리", "2266": "논법", "2267": "큰일", "2268": "스틱스", "2269": "감옥", "2270": "약자", "2271": "자고", "2272": "굴지", "2273": "라라", "2274": "혹시", "2275": "기시감", "2276": "예전", "2277": "이건희", "2278": "선친", "2279": "거짓말", "2280": "평창동계올림픽", "2281": "어쨌든", "2282": "궁극", "2283": "말씀", "2284": "시점", "2285": "온라인", "2286": "상속세", "2287": "납부", "2288": "마감", "2289": "기증", "2290": "공식", "2291": "예고", "2292": "공판", "2293": "소문", "2294": "재산", "2295": "환원", "2296": "계획", "2297": "움직임", "2298": "따라서", "2299": "타이밍", "2300": "공교롭", "2301": "양쪽", "2302": "조율", "2303": "지론", "2304": "출입", "2305": "마침", "2306": "의도", "2307": "분란", "2308": "어쩜", "2309": "색깔", "2310": "자체", "2311": "마찬가지", "2312": "헤드라인", "2313": "세금", "2314": "시청자", "2315": "사회자", "2316": "분도", "2317": "소득세", "2318": "달유", "2319": "개혁", "2320": "자꾸만", "2321": "잣", "2322": "이건", "2323": "정의", "2324": "전하", "2325": "성향", "2326": "차이", "2327": "일례", "2328": "회견", "2329": "전직", "2330": "경향신문", "2331": "측면", "2332": "자사", "2333": "피니언", "2334": "칼럼", "2335": "사설", "2336": "남짓", "2337": "찬성", "2338": "매일경제", "2339": "한겨레", "2340": "신문", "2341": "개진", "2342": "자꾸", "2343": "사면권", "2344": "배려", "2345": "법치", "2346": "폭력", "2347": "면허", "2348": "특별사면", "2349": "식", "2350": "여유", "2351": "독자", "2352": "분리", "2353": "배연", "2354": "제목", "2355": "하라", "2356": "존재", "2357": "봄", "2358": "이순신", "2359": "장군", "2360": "압송", "2361": "본인", "2362": "장수", "2363": "노골", "2364": "균형", "2365": "어려움", "2366": "인맥", "2367": "한창", "2368": "난항", "2369": "돌파구", "2370": "마련", "2371": "근거", "2372": "정계", "2373": "소위", "2374": "답정너", "2375": "저널리즘", "2376": "걱정", "2377": "불철", "2378": "주야", "2379": "제일", "2380": "영향력", "2381": "류", "2382": "물량", "2383": "막후", "2384": "이형인", "2385": "동작구", "2386": "계세", "2387": "버티고", "2388": "탈락", "2389": "권영규", "2390": "금천구", "2391": "선생님", "2392": "이세", "2393": "공헌", "2394": "김진", "2395": "석", "2396": "경기", "2397": "고양시", "2398": "개인", "2399": "여론", "2400": "데일리안", "2401": "민심", "2402": "설문", "2403": "문항", "2404": "앞뒤", "2405": "심층", "2406": "압도", "2407": "그거", "2408": "이례", "2409": "수치", "2410": "자의", "2411": "해석", "2412": "부인", "2413": "각자", "2414": "비평", "2415": "프로그램", "2416": "짓", "2417": "장충", "2418": "이분", "2419": "문자", "2420": "언론인", "2421": "사적", "2422": "설마", "2423": "문자메시지", "2424": "학계", "2425": "법조", "2426": "국장", "2427": "눈", "2428": "고요", "2429": "혈맹입니", "2430": "소속", "2431": "사장", "2432": "하해", "2433": "은혜", "2434": "앙망", "2435": "읍소", "2436": "경제권", "2437": "고문", "2438": "김세형", "2439": "매경", "2440": "주필", "2441": "논설", "2442": "발령", "2443": "과분", "2444": "결단", "2445": "신념", "2446": "거스", "2447": "지도자", "2448": "음", "2449": "홍보", "2450": "실장", "2451": "상관", "2452": "이철호", "2453": "논설주간", "2454": "와인", "2455": "번역기", "2456": "친문", "2457": "언어", "2458": "대가", "2459": "분위기", "2460": "전화통화", "2461": "미디어비평", "2462": "간다", "2463": "곧바로", "2464": "통한", "2465": "일명", "2466": "파장", "2467": "치욕", "2468": "영화", "2469": "덕후", "2470": "대사", "2471": "봄날", "2472": "유지태", "2473": "비현실적", "2474": "은정", "2475": "지탄", "2476": "불구", "2477": "단죄", "2478": "공론", "2479": "종", "2480": "비롯", "2481": "타임즈", "2482": "트럼프", "2483": "보고서", "2484": "향후", "2485": "콘텐츠", "2486": "퀄리티", "2487": "페이퍼", "2488": "증가", "2489": "부수", "2490": "발행", "2491": "개척", "2492": "응원", "2493": "환호", "2494": "승부", "2495": "뉴욕타임즈", "2496": "어쩌면", "2497": "합", "2498": "단연", "2499": "부동", "2500": "연간", "2501": "파이", "2502": "영역", "2503": "두려움", "2504": "드릴", "2505": "결론", "2506": "흑자", "2507": "때로는", "2508": "반성", "2509": "공영", "2510": "재원", "2511": "수신료", "2512": "재벌", "2513": "권력", "2514": "눈길", "2515": "섭", "2516": "해법", "2517": "협찬", "2518": "신문사", "2519": "주요", "2520": "수입", "2521": "열", "2522": "명도", "2523": "홍석우", "2524": "자수", "2525": "오정", "2526": "림", "2527": "꼬박꼬박", "2528": "페이지", "2529": "옥천", "2530": "모집", "2531": "충청북도", "2532": "옥천군", "2533": "다가", "2534": "밑줄", "2535": "요새", "2536": "종이", "2537": "쇠퇴", "2538": "이중고", "2539": "구독", "2540": "률", "2541": "비결", "2542": "진과", "2543": "군청소재지", "2544": "읍내", "2545": "대청호", "2546": "줄기", "2547": "거슬러", "2548": "산골", "2549": "안남면", "2550": "겨울", "2551": "태양광", "2552": "개발", "2553": "시위", "2554": "군청", "2555": "덮힌", "2556": "설치", "2557": "정지", "2558": "덕실", "2559": "밑", "2560": "운동", "2561": "시피", "2562": "진짜", "2563": "헥헥", "2564": "거릴", "2565": "축구장", "2566": "보류", "2567": "무렵", "2568": "읍", "2569": "세탁소", "2570": "아주머니", "2571": "차별", "2572": "민호", "2573": "상임", "2574": "나머지", "2575": "어미", "2576": "주렁주렁", "2577": "굳이", "2578": "출입처", "2579": "보도자료", "2580": "의존", "2581": "공무원", "2582": "직책", "2583": "귀", "2584": "전교생", "2585": "배달", "2586": "구석구석", "2587": "박연", "2588": "도서관", "2589": "활동가", "2590": "곳곳", "2591": "순환", "2592": "매출", "2593": "구독료", "2594": "충", "2595": "성도", "2596": "료", "2597": "비중", "2598": "광고주", "2599": "입김", "2600": "최소한", "2601": "마지노선", "2602": "이외", "2603": "자본", "2604": "박해", "2605": "윤", "2606": "군정", "2607": "담", "2608": "살기", "2609": "주리", "2610": "추복", "2611": "충북", "2612": "방향", "2613": "제작", "2614": "편집", "2615": "학생", "2616": "역사", "2617": "편집국", "2618": "독립운동", "2619": "산지", "2620": "덕", "2621": "입사", "2622": "몰려듭니", "2623": "이현경", "2624": "나이", "2625": "살이", "2626": "생", "2627": "부조리", "2628": "보탬", "2629": "마음가짐", "2630": "조회", "2631": "평균", "2632": "의회", "2633": "답글", "2634": "리기", "2635": "권오성", "2636": "칙", "2637": "수칙", "2638": "윤전기", "2639": "펜", "2640": "삭", "2641": "밤", "2642": "돌", "2643": "배송", "2644": "할머니", "2645": "일어나서", "2646": "이면", "2647": "금요일", "2648": "웃음", "2649": "군민", "2650": "주주", "2651": "창간", "2652": "민", "2653": "밀착", "2654": "얼마만큼", "2655": "벌레", "2656": "세밀", "2657": "일요일", "2658": "텍스트", "2659": "이데일리", "2660": "박순", "2661": "엽", "2662": "이상원", "2663": "반포", "2664": "집회", "2665": "오프라인", "2666": "죽음", "2667": "제대로", "2668": "모씨", "2669": "규명", "2670": "통합", "2671": "주최", "2672": "인원", "2673": "제한", "2674": "인", "2675": "금지", "2676": "방", "2677": "최대", "2678": "참가자", "2679": "접속", "2680": "제발", "2681": "대별", "2682": "일상", "2683": "토", "2684": "허수아비", "2685": "문구", "2686": "손뼉", "2687": "고개", "2688": "끄덕", "2689": "익사", "2690": "시신", "2691": "혈", "2692": "청원", "2693": "전환", "2694": "이튿날", "2695": "휴대전화", "2696": "상세", "2697": "기지국", "2698": "신호", "2699": "재", "2700": "추모", "2701": "공간", "2702": "스크린", "2703": "접근", "2704": "질서", "2705": "오픈", "2706": "대화방", "2707": "추진", "2708": "실족", "2709": "방장", "2710": "표명", "2711": "방법", "2712": "사전", "2713": "이하", "2714": "행진", "2715": "법률", "2716": "아쉬움", "2717": "부방", "2718": "부각", "2719": "색도", "2720": "김씨", "2721": "각지", "2722": "비용", "2723": "모금", "2724": "메모", "2725": "이름", "2726": "초성", "2727": "모양", "2728": "조물", "2729": "블랙박스", "2730": "법무부", "2731": "상반기", "2732": "검찰청", "2733": "조직", "2734": "개편안", "2735": "지방검찰청", "2736": "부패", "2737": "사부", "2738": "전담", "2739": "공문", "2740": "분장사", "2741": "무인", "2742": "외한", "2743": "검찰총장", "2744": "승인", "2745": "개시", "2746": "공직자", "2747": "비리", "2748": "고발장", "2749": "이성윤", "2750": "하의", "2751": "손발", "2752": "묶인", "2753": "일선", "2754": "사정", "2755": "조처", "2756": "김학의", "2757": "기획", "2758": "출국금지", "2759": "수원지검", "2760": "월성", "2761": "호기", "2762": "원자력발전소", "2763": "폐쇄", "2764": "이상직", "2765": "대전", "2766": "부와", "2767": "주지", "2768": "말부", "2769": "법무", "2770": "김남준", "2771": "폐지", "2772": "권고", "2773": "사법", "2774": "주체", "2775": "재임", "2776": "총장", "2777": "강력", "2778": "부로", "2779": "통폐합", "2780": "부서", "2781": "신설", "2782": "노태우", "2783": "메카", "2784": "직제", "2785": "개편", "2786": "강력범죄", "2787": "명패", "2788": "명맥", "2789": "운명", "2790": "폭력조직", "2791": "조작", "2792": "점령", "2793": "감돈", "2794": "동시", "2795": "초점", "2796": "추미애", "2797": "범죄수사", "2798": "부활", "2799": "남부", "2800": "가칭", "2801": "비직", "2802": "합동", "2803": "취약", "2804": "라임", "2805": "옵티머스", "2806": "금융감독원", "2807": "유관", "2808": "상시", "2809": "필요성", "2810": "검경", "2811": "수사권", "2812": "조정", "2813": "피의자", "2814": "김영기", "2815": "타", "2816": "여권", "2817": "희망", "2818": "보직", "2819": "지망", "2820": "통보", "2821": "편이", "2822": "후보자", "2823": "단행", "2824": "대적", "2825": "밑그림", "2826": "구애", "2827": "유원", "2828": "모", "2829": "어제", "2830": "협조", "2831": "필름", "2832": "악의", "2833": "루머", "2834": "법적", "2835": "서준석", "2836": "뒷받침", "2837": "정근", "2838": "목격", "2839": "주차장", "2840": "단편", "2841": "취했느", "2842": "취하", "2843": "축", "2844": "측도", "2845": "그날", "2846": "뭘", "2847": "불가능", "2848": "인신공격", "2849": "감히", "2850": "비극", "2851": "악플", "2852": "비난", "2853": "저주", "2854": "종아리", "2855": "혈액", "2856": "동맥", "2857": "온몸", "2858": "정맥", "2859": "펌프", "2860": "부종", "2861": "장애", "2862": "결합", "2863": "확장", "2864": "중년", "2865": "당뇨병", "2866": "고혈압", "2867": "비만", "2868": "임신", "2869": "호르몬", "2870": "복용", "2871": "폐경", "2872": "갱년기", "2873": "고정", "2874": "자세", "2875": "직업", "2876": "더욱더", "2877": "남녀", "2878": "유병률", "2879": "자궁", "2880": "압박", "2881": "과체중", "2882": "혈류", "2883": "주기", "2884": "하체", "2885": "의복", "2886": "다리", "2887": "무리", "2888": "하이힐", "2889": "부족", "2890": "발", "2891": "발목", "2892": "발바닥", "2893": "화끈", "2894": "반복", "2895": "저리", "2896": "쥐", "2897": "피부", "2898": "가렵다", "2899": "혈관", "2900": "안전지대", "2901": "명꼴", "2902": "발현", "2903": "율", "2904": "낮", "2905": "방치", "2906": "하지정맥류", "2907": "보험", "2908": "공단", "2909": "술통", "2910": "결찰", "2911": "매듭", "2912": "제거", "2913": "수술", "2914": "건수", "2915": "벽", "2916": "걷기", "2917": "수영", "2918": "근육", "2919": "정맥혈", "2920": "촉진", "2921": "탄력", "2922": "모세혈관", "2923": "투과성", "2924": "정상화", "2925": "센텔", "2926": "정량", "2927": "추출", "2928": "개선", "2929": "체중", "2930": "음식", "2931": "조절", "2932": "신발", "2933": "신기", "2934": "흡연", "2935": "음주", "2936": "자제", "2937": "요법", "2938": "병행", "2939": "효과", "2940": "찜질", "2941": "마사지", "2942": "호전", "2943": "일시", "2944": "증", "2945": "잠시", "2946": "증상만", "2947": "완화", "2948": "이재영", "2949": "올여름", "2950": "조지아주", "2951": "애틀랜타", "2952": "비행", "2953": "여행객", "2954": "환승", "2955": "짐", "2956": "국토안보부", "2957": "과학기술", "2958": "국토교통부", "2959": "클라우드", "2960": "수하물", "2961": "격", "2962": "시범", "2963": "국토부", "2964": "출발", "2965": "엑스레이", "2966": "항공기", "2967": "원격", "2968": "인천", "2969": "국제공항", "2970": "하츠", "2971": "필드", "2972": "노선", "2973": "델타항공", "2974": "착륙", "2975": "보안요원", "2976": "세관", "2977": "보호국", "2978": "환", "2979": "승객", "2980": "재검사", "2981": "횟수", "2982": "배포", "2983": "바탕", "2984": "입국", "2985": "수속", "2986": "소요", "2987": "위탁", "2988": "자원", "2989": "대면", "2990": "효율", "2991": "객", "2992": "이익", "2993": "한계", "2994": "펠", "2995": "자문", "2996": "노출", "2997": "실패", "2998": "연내", "2999": "시진핑", "3000": "국가주석", "3001": "방한", "3002": "호성", "3003": "내비", "3004": "칠", "3005": "우려", "3006": "김형준", "3007": "명지대", "3008": "외교학", "3009": "얻지", "3010": "지지율", "3011": "임기", "3012": "속성", "3013": "핵심", "3014": "정인교", "3015": "인하대", "3016": "학과", "3017": "재창", "3018": "고리", "3019": "속마음", "3020": "수위", "3021": "주저", "3022": "국방위원장", "3023": "원목", "3024": "이화여대", "3025": "법학", "3026": "전문", "3027": "대학원", "3028": "국면", "3029": "합류", "3030": "시그널", "3031": "견제", "3032": "기조", "3033": "연동", "3034": "쟁권", "3035": "실천", "3036": "지층", "3037": "자축", "3038": "대감", "3039": "증설", "3040": "애", "3041": "카드", "3042": "오류", "3043": "일침", "3044": "세종", "3045": "연구소", "3046": "수립", "3047": "정치권", "3048": "상승", "3049": "내기", "3050": "반향", "3051": "신율", "3052": "노무현", "3053": "남북정상회담", "3054": "이벤트", "3055": "대폭", "3056": "스와프", "3057": "무산", "3058": "실적", "3059": "박진용", "3060": "실속", "3061": "이득", "3062": "다섯", "3063": "규칙", "3064": "규범", "3065": "지목", "3066": "양안", "3067": "남중국해", "3068": "신장", "3069": "위구르", "3070": "아예", "3071": "저해", "3072": "우회", "3073": "함축", "3074": "자유", "3075": "인도", "3076": "태평양", "3077": "태", "3078": "폭", "3079": "구체화", "3080": "팩트", "3081": "시트", "3082": "영어", "3083": "당국자", "3084": "한반도", "3085": "결의", "3086": "준수", "3087": "불가", "3088": "역적", "3089": "핵", "3090": "셈", "3091": "응용", "3092": "여섯", "3093": "박현주", "3094": "어디", "3095": "전초", "3096": "자화상", "3097": "가슴", "3098": "수행", "3099": "하트", "3100": "휴대폰", "3101": "헬스장", "3102": "역기", "3103": "등등", "3104": "그림", "3105": "년", "3106": "작가", "3107": "형상", "3108": "박생광", "3109": "선생", "3110": "단청", "3111": "탱화", "3112": "민화", "3113": "무속", "3114": "화란", "3115": "불교", "3116": "미술", "3117": "구사", "3118": "절정", "3119": "색채", "3120": "완성", "3121": "그이", "3122": "이쯤", "3123": "으레", "3124": "신자", "3125": "되레", "3126": "외가", "3127": "기독교", "3128": "집안", "3129": "골프", "3130": "치장", "3131": "애정", "3132": "행각", "3133": "모던", "3134": "남", "3135": "숱", "3136": "리나", "3137": "그린", "3138": "범신론", "3139": "스타일", "3140": "사람과", "3141": "예수", "3142": "마호메트", "3143": "부처상", "3144": "족", "3145": "삼삼", "3146": "화업", "3147": "포스트모더니즘", "3148": "선두", "3149": "품세", "3150": "꽃", "3151": "식물학", "3152": "연작", "3153": "서사", "3154": "특화", "3155": "동양", "3156": "유일", "3157": "무", "3158": "보물", "3159": "현대", "3160": "성상", "3161": "라면", "3162": "별의별", "3163": "기웃", "3164": "거린", "3165": "그대", "3166": "커피", "3167": "술병", "3168": "얘깃", "3169": "종교인", "3170": "차마", "3171": "소시민", "3172": "동화", "3173": "몹시", "3174": "가르침", "3175": "주기도", "3176": "역설", "3177": "씨앗", "3178": "상상력", "3179": "상상", "3180": "붓", "3181": "아무나", "3182": "산다", "3183": "의외", "3184": "예술", "3185": "예술가", "3186": "전시", "3187": "매번", "3188": "진화", "3189": "한우물", "3190": "고집", "3191": "권", "3192": "산책", "3193": "주의자", "3194": "사생활", "3195": "삽화", "3196": "무작정", "3197": "풍경", "3198": "밍사산", "3199": "모래사막", "3200": "둔황", "3201": "리다", "3202": "덩어리", "3203": "사방", "3204": "장구", "3205": "오현주", "3206": "대형견", "3207": "영재", "3208": "시베리아", "3209": "원산지", "3210": "잡종견", "3211": "나물", "3212": "사모님", "3213": "아유", "3214": "행인", "3215": "출혈", "3216": "심해", "3217": "며칠", "3218": "동네", "3219": "출몰", "3220": "집사람", "3221": "저쪽", "3222": "가해견", "3223": "다방면", "3224": "외지", "3225": "염두", "3226": "시청", "3227": "인필", "3228": "소방", "3229": "돌발", "3230": "블룸버그", "3231": "진보", "3232": "마법", "3233": "구별", "3234": "트윗", "3235": "누리꾼", "3236": "네티즌", "3237": "즉답", "3238": "동문서답", "3239": "전투", "3240": "후자", "3241": "쓰레기", "3242": "화성", "3243": "로서", "3244": "동등", "3245": "돌연", "3246": "악", "3247": "방아쇠", "3248": "원화", "3249": "반토막", "3250": "은빛", "3251": "한경닷컴", "3252": "무단", "3253": "정진", "3254": "차기", "3255": "적합", "3256": "돌풍", "3257": "양상", "3258": "쿠키뉴스", "3259": "일인", "3260": "원내대표", "3261": "포인트", "3262": "오차", "3263": "범위", "3264": "홍문표", "3265": "윤영석", "3266": "조경태", "3267": "모름", "3268": "응답", "3269": "기타", "3270": "강원", "3271": "제주", "3272": "중도", "3273": "호남권", "3274": "미래한국", "3275": "피플", "3276": "네트웍", "3277": "무당", "3278": "성별", "3279": "전주", "3280": "지역별", "3281": "무선", "3282": "유선", "3283": "무작위", "3284": "표본", "3285": "신뢰수준", "3286": "성북구", "3287": "회관", "3288": "삼삼오오", "3289": "벤치", "3290": "계단", "3291": "술자리", "3292": "음악", "3293": "웃음소리", "3294": "교내", "3295": "일행", "3296": "실외", "3297": "취식", "3298": "의무", "3299": "착용", "3300": "현수막", "3301": "눈치", "3302": "맥주", "3303": "전모", "3304": "술집", "3305": "편의점", "3306": "사서", "3307": "박모", "3308": "골목", "3309": "동대문구", "3310": "본관", "3311": "컵라면", "3312": "과자", "3313": "신입생", "3314": "전부", "3315": "취소", "3316": "맘", "3317": "아르바이트생", "3318": "차모", "3319": "매일", "3320": "안줏거리", "3321": "셧다운", "3322": "캠퍼스", "3323": "대학가", "3324": "가게", "3325": "날씨", "3326": "안주", "3327": "주차", "3328": "개방", "3329": "현행법", "3330": "방지", "3331": "폴리스", "3332": "순찰", "3333": "외주", "3334": "경비", "3335": "확성기", "3336": "해산", "3337": "인력", "3338": "야간", "3339": "관할", "3340": "동대문", "3341": "구청", "3342": "북구청", "3343": "모임", "3344": "과태료", "3345": "고지서", "3346": "부과", "3347": "도하", "3348": "김성철", "3349": "고려대", "3350": "장기", "3351": "화로", "3352": "교육", "3353": "질", "3354": "달성", "3355": "지혜", "3356": "공군", "3357": "김현수", "3358": "비행단", "3359": "영접", "3360": "공급망", "3361": "자동차", "3362": "라운드테이블", "3363": "직스", "3364": "나사", "3365": "생산", "3366": "연구개발", "3367": "양해각서", "3368": "체결", "3369": "알링턴", "3370": "국립묘지", "3371": "헌화", "3372": "사자", "3373": "착공", "3374": "영웅", "3375": "영예", "3376": "개국", "3377": "만날", "3378": "민우", "3379": "재희", "3380": "고령", "3381": "예방접종", "3382": "현행", "3383": "수도권", "3384": "유흥", "3385": "시설", "3386": "집합", "3387": "카페", "3388": "체육", "3389": "연습장", "3390": "판매", "3391": "여건", "3392": "명인", "3393": "명대", "3394": "격상", "3395": "종은", "3396": "시간제", "3397": "지방자치단체", "3398": "자율", "3399": "부여", "3400": "거주", "3401": "직계", "3402": "존비속", "3403": "미만", "3404": "영유", "3405": "아동", "3406": "노인", "3407": "장애인", "3408": "임종", "3409": "상견례", "3410": "예외", "3411": "풋살", "3412": "관리자", "3413": "스포츠", "3414": "단란", "3415": "감성", "3416": "주점", "3417": "콜", "3418": "라텍", "3419": "무도장", "3420": "헌팅", "3421": "포차", "3422": "홀덤", "3423": "펍", "3424": "매장", "3425": "허용", "3426": "파티", "3427": "룸", "3428": "스탠딩", "3429": "공연장", "3430": "사우나", "3431": "영화관", "3432": "좌석", "3433": "칸", "3434": "동반", "3435": "관람", "3436": "정원", "3437": "결혼식장", "3438": "전시회", "3439": "박람회", "3440": "면적", "3441": "알코올", "3442": "음료", "3443": "섭취", "3444": "백화점", "3445": "마트", "3446": "휴식", "3447": "정규", "3448": "예배", "3449": "미사", "3450": "법회", "3451": "시일", "3452": "원주시", "3453": "태백시", "3454": "해제", "3455": "디저트", "3456": "주문", "3457": "협의", "3458": "숙박", "3459": "전남", "3460": "시행", "3461": "관찰", "3462": "발걸음", "3463": "수상택시", "3464": "승강장", "3465": "피켓", "3466": "중앙대", "3467": "의대", "3468": "본과", "3469": "학년", "3470": "잠", "3471": "닷새", "3472": "수중", "3473": "부검", "3474": "연초", "3475": "횡보", "3476": "코스피", "3477": "하반기", "3478": "대체로", "3479": "열기", "3480": "유동성", "3481": "금융투자", "3482": "증권사", "3483": "가파른", "3484": "기류", "3485": "종가", "3486": "인플레이션", "3487": "긴축", "3488": "장밋빛", "3489": "상", "3490": "장사", "3491": "대비", "3492": "순이익", "3493": "점프", "3494": "수출", "3495": "소비", "3496": "덕이", "3497": "중혁", "3498": "시중금리", "3499": "방향성", "3500": "경신", "3501": "수익률", "3502": "동기", "3503": "상향", "3504": "주식시장", "3505": "좀처럼", "3506": "긍정", "3507": "폭락", "3508": "쓰나미", "3509": "열흘", "3510": "원대", "3511": "복사", "3512": "외치", "3513": "판", "3514": "안정감", "3515": "탁금", "3516": "금은", "3517": "모주", "3518": "청약", "3519": "이경민", "3520": "대금", "3521": "안착", "3522": "극복", "3523": "곽주현", "3524": "도쿄", "3525": "세원", "3526": "올림픽", "3527": "개막", "3528": "신종", "3529": "코로나바이러스", "3530": "감염증", "3531": "사망자", "3532": "축소", "3533": "교도통신", "3534": "선포", "3535": "분류", "3536": "판정", "3537": "중증", "3538": "오키나와", "3539": "현", "3540": "발효", "3541": "도쿄도", "3542": "광역", "3543": "자치", "3544": "설정", "3545": "가토", "3546": "노부", "3547": "관방", "3548": "관해", "3549": "지표", "3550": "오사카", "3551": "자위대", "3552": "속도", "3553": "구상", "3554": "예약", "3555": "오류로", "3556": "혼선", "3557": "도쿄올림픽", "3558": "매달", "3559": "요금", "3560": "통신사", "3561": "환불", "3562": "유플러스", "3563": "대리점", "3564": "적반하장", "3565": "승종", "3566": "구형", "3567": "이동통신", "3568": "서비스", "3569": "곧", "3570": "번호", "3571": "개통", "3572": "제보자", "3573": "음성", "3574": "변조", "3575": "폰", "3576": "누락", "3577": "폐점", "3578": "임대", "3579": "청구", "3580": "정지연", "3581": "소비자", "3582": "연맹", "3583": "사무", "3584": "장기간", "3585": "모니터링", "3586": "방통위", "3587": "분쟁", "3588": "이나", "3589": "촬영기", "3590": "박세준", "3591": "유지영", "3592": "그래픽", "3593": "김지훈", "3594": "남승렬", "3595": "권영진", "3596": "대구시", "3597": "망인", "3598": "바이러스", "3599": "자화자찬", "3600": "평가절하", "3601": "장병", "3602": "미리", "3603": "자랑", "3604": "급", "3605": "야당", "3606": "정치인", "3607": "치사", "3608": "양반", "3609": "한마디", "3610": "어쩌다가", "3611": "국군", "3612": "원조", "3613": "감읍", "3614": "해하", "3615": "개념", "3616": "어이", "3617": "고작", "3618": "연합", "3619": "훈련", "3620": "극적", "3621": "작심", "3622": "봉착", "3623": "수급", "3624": "전선", "3625": "납득", "3626": "나름", "3627": "최선", "3628": "다", "3629": "관건", "3630": "올인", "3631": "연달", "3632": "광역시", "3633": "반면", "3634": "옹호", "3635": "파운드리", "3636": "가동", "3637": "뚜껑", "3638": "센티", "3639": "브", "3640": "김기남", "3641": "텍사스", "3642": "애리조나", "3643": "뉴욕주", "3644": "유치", "3645": "확정", "3646": "변수", "3647": "세제", "3648": "인센티브", "3649": "텍사스주", "3650": "커뮤니티", "3651": "임팩트", "3652": "환급", "3653": "오스틴", "3654": "시가", "3655": "고도", "3656": "서류", "3657": "투자가", "3658": "간접", "3659": "고용", "3660": "채용", "3661": "혜택", "3662": "액", "3663": "지로", "3664": "부지", "3665": "경매", "3666": "유찰", "3667": "건설", "3668": "보조금", "3669": "용수", "3670": "감축", "3671": "문승욱", "3672": "통상부", "3673": "러몬", "3674": "약속", "3675": "인프라", "3676": "지방정부", "3677": "연방", "3678": "조중휘", "3679": "인천대", "3680": "임베디드", "3681": "전기", "3682": "세부", "3683": "적지", "3684": "수요", "3685": "엔비디아", "3686": "팹리스", "3687": "박형수", "3688": "식품의약품안전처", "3689": "식품", "3690": "푸른", "3691": "생선", "3692": "오메가", "3693": "지방산", "3694": "음식물", "3695": "불포화지방산", "3696": "함유", "3697": "계열", "3698": "혈압", "3699": "강하", "3700": "동맥경화", "3701": "심장질환", "3702": "발병", "3703": "섭취량", "3704": "급성", "3705": "심근경색증", "3706": "뇌졸중", "3707": "한국인", "3708": "통계청", "3709": "뇌혈관", "3710": "합치", "3711": "심뇌", "3712": "통계", "3713": "선행", "3714": "콜레스테롤", "3715": "증도", "3716": "이처럼", "3717": "혈행", "3718": "치매", "3719": "유의", "3720": "현황", "3721": "비율", "3722": "알츠하이머", "3723": "습관", "3724": "식생활", "3725": "과식", "3726": "동물성", "3727": "포화지방", "3728": "경화", "3729": "식물성", "3730": "육류", "3731": "버터", "3732": "치즈", "3733": "마가린", "3734": "마요네즈", "3735": "가공", "3736": "옥수수", "3737": "리놀렌산", "3738": "일종", "3739": "견과류", "3740": "올리브유", "3741": "정식", "3742": "원료", "3743": "명칭", "3744": "세포막", "3745": "세포", "3746": "신진대사", "3747": "체내", "3748": "보충", "3749": "혈중", "3750": "중성", "3751": "지질", "3752": "뇌", "3753": "신경조직", "3754": "망막", "3755": "순도", "3756": "분자", "3757": "자연계", "3758": "즉", "3759": "보통", "3760": "국회", "3761": "본회의", "3762": "혼란", "3763": "혼돈", "3764": "자산", "3765": "공언", "3766": "발자국", "3767": "변화", "3768": "주무", "3769": "입법", "3770": "무책임", "3771": "무방비", "3772": "생기지", "3773": "이전", "3774": "실태", "3775": "고음", "3776": "벌집", "3777": "경의", "3778": "법인", "3779": "정황", "3780": "포착", "3781": "실시간", "3782": "발동", "3783": "테스", "3784": "포스", "3785": "출범", "3786": "추방", "3787": "작전", "3788": "철퇴", "3789": "육성", "3790": "런", "3791": "방위", "3792": "출금", "3793": "소닉", "3794": "출하", "3795": "가시", "3796": "경은", "3797": "즉각", "3798": "동결", "3799": "조권", "3800": "창시자", "3801": "릭", "3802": "린", "3803": "후일", "3804": "예측", "3805": "곤두박질", "3806": "장난감", "3807": "탄소", "3808": "다량", "3809": "배출", "3810": "잡", "3811": "유명인", "3812": "널", "3813": "파괴", "3814": "지남", "3815": "면역", "3816": "일절", "3817": "경청", "3818": "대립", "3819": "신혜", "3820": "연", "3821": "빌라", "3822": "밀집", "3823": "중랑구", "3824": "망우", "3825": "지하철역", "3826": "한참", "3827": "절레절레", "3828": "망우역", "3829": "재래시장", "3830": "경전철", "3831": "목선", "3832": "부동산", "3833": "대중교통", "3834": "접근성", "3835": "강북", "3836": "강남구", "3837": "환승역", "3838": "중복", "3839": "노원구", "3840": "박홍근", "3841": "전철역", "3842": "행정동", "3843": "도봉", "3844": "성북", "3845": "서대문", "3846": "노원", "3847": "근로", "3848": "통일", "3849": "출퇴근", "3850": "통일로", "3851": "진척", "3852": "도봉구", "3853": "선도", "3854": "차선", "3855": "행선", "3856": "삽도", "3857": "서민", "3858": "쌍문", "3859": "동", "3860": "방학", "3861": "동도", "3862": "베이", "3863": "직장", "3864": "출근", "3865": "통근", "3866": "불편", "3867": "겹친", "3868": "쌍문동", "3869": "강남", "3870": "버스", "3871": "이사", "3872": "교통", "3873": "동북", "3874": "체증", "3875": "월계", "3876": "교", "3877": "간선", "3878": "통행량", "3879": "태릉", "3880": "골프장", "3881": "지옥", "3882": "지하철", "3883": "송파구", "3884": "동이", "3885": "셋", "3886": "도심", "3887": "격자", "3888": "계획도시", "3889": "신도시", "3890": "택지", "3891": "분당", "3892": "수원", "3893": "용인", "3894": "위주", "3895": "가속", "3896": "호선", "3897": "수서", "3898": "오금", "3899": "구간", "3900": "신분당선", "3901": "수인", "3902": "분당선", "3903": "망", "3904": "고속버스", "3905": "터미널", "3906": "제로", "3907": "개년", "3908": "도시철도", "3909": "영등포구", "3910": "샛강역", "3911": "관악구", "3912": "서울대", "3913": "신림선", "3914": "내년", "3915": "성동구", "3916": "왕십리역", "3917": "상계역", "3918": "북선", "3919": "중간", "3920": "삽", "3921": "청량리", "3922": "신내", "3923": "목동", "3924": "신월동", "3925": "예비", "3926": "타당성", "3927": "우이", "3928": "장선", "3929": "경제성", "3930": "재정", "3931": "횡", "3932": "단선", "3933": "철도", "3934": "수혜자", "3935": "통행", "3936": "미지수", "3937": "배점", "3938": "혜림", "3939": "유동", "3940": "구가", "3941": "점수", "3942": "로만", "3943": "하성", "3944": "노", "3945": "곱사등이", "3946": "보지", "3947": "트집", "3948": "부시", "3949": "회동했다", "3950": "보수", "3951": "참여정부", "3952": "최악", "3953": "사후", "3954": "자전거", "3955": "기분", "3956": "특유", "3957": "감탄사", "3958": "연발", "3959": "서거", "3960": "추도", "3961": "람사", "3962": "상전", "3963": "인사동", "3964": "마루", "3965": "아트", "3966": "발열", "3967": "체크", "3968": "노소", "3969": "북적", "3970": "둘러보기", "3971": "작품", "3972": "감상", "3973": "쪽지", "3974": "가득", "3975": "찬", "3976": "초등학생", "3977": "삐뚤빼뚤", "3978": "정성껏", "3979": "위상", "3980": "공화당", "3981": "꿈", "3982": "유홍준", "3983": "문화재", "3984": "청장", "3985": "곽노현", "3986": "교육감", "3987": "박재동", "3988": "만화가", "3989": "서양화", "3990": "인물화", "3991": "만화", "3992": "서예", "3993": "조각", "3994": "마주", "3995": "미소", "3996": "재직", "3997": "퇴임", "3998": "승화", "3999": "장르", "4000": "망라", "4001": "인상", "4002": "여럿", "4003": "개막식", "4004": "유시민", "4005": "노무현재단", "4006": "이사장", "4007": "축사", "4008": "그리움", "4009": "맥락", "4010": "축하", "4011": "정면", "4012": "출품", "4013": "상일", "4014": "전속", "4015": "사진사", "4016": "장철", "4017": "사진전", "4018": "다큐", "4019": "멘턴", "4020": "무현", "4021": "역대", "4022": "포토제닉", "4023": "다수", "4024": "복기", "4025": "공교", "4026": "시즌", "4027": "야심", "4028": "밴드", "4029": "오스카상", "4030": "기생충", "4031": "찌", "4032": "감치", "4033": "예견", "4034": "당선", "4035": "대거리", "4036": "일환", "4037": "인류", "4038": "세기", "4039": "팽창", "4040": "출산율", "4041": "사망률", "4042": "급속도", "4043": "산부인과", "4044": "독일", "4045": "빈집", "4046": "체감", "4047": "멕시코", "4048": "합계출산율", "4049": "놀이터", "4050": "잡초", "4051": "무성", "4052": "병합", "4053": "공업", "4054": "대의", "4055": "유령도시", "4056": "나이지리아", "4057": "도전", "4058": "저하", "4059": "노동자", "4060": "은퇴", "4061": "요인", "4062": "프랑크", "4063": "스비아츠", "4064": "부국", "4065": "캘리포니아주", "4066": "고속도로", "4067": "보복", "4068": "운전", "4069": "시비", "4070": "총격", "4071": "등교", "4072": "하얀색", "4073": "세단", "4074": "다툼", "4075": "변경", "4076": "욕설", "4077": "제스처", "4078": "취했다", "4079": "총성", "4080": "발사", "4081": "총알", "4082": "오른쪽", "4083": "자석", "4084": "비명", "4085": "소리", "4086": "승자", "4087": "책임자", "4088": "로렌", "4089": "티노", "4090": "리베", "4091": "쏠", "4092": "정당성", "4093": "가해자", "4094": "양재영", "4095": "참사", "4096": "대검찰청", "4097": "취합", "4098": "국무회의", "4099": "용지", "4100": "부의", "4101": "제약", "4102": "역량", "4103": "허락", "4104": "치명", "4105": "계절", "4106": "독감", "4107": "상승세", "4108": "안쪽", "4109": "김우주", "4110": "내과", "4111": "고령자", "4112": "정재훈", "4113": "가천대", "4114": "예방의학", "4115": "극단", "4116": "요양", "4117": "대본", "4118": "성남", "4119": "미접", "4120": "종자", "4121": "마상", "4122": "혁", "4123": "신학회", "4124": "경남", "4125": "진주", "4126": "세계보건기구", "4127": "오명", "4128": "근절", "4129": "중환자", "4130": "학기", "4131": "전면", "4132": "개학", "4133": "벗", "4134": "변", "4135": "각심", "4136": "수연", "4137": "이목", "4138": "도출", "4139": "후임", "4140": "부임", "4141": "유독", "4142": "무소식", "4143": "강제", "4144": "처분", "4145": "신임", "4146": "후속", "4147": "감지", "4148": "수뇌부", "4149": "당사자", "4150": "한동훈", "4151": "무혐의", "4152": "불기소", "4153": "결재", "4154": "차일피일", "4155": "요지부동", "4156": "이동재", "4157": "정작", "4158": "코바", "4159": "컨텐츠", "4160": "금", "4161": "명목", "4162": "금품", "4163": "수수", "4164": "도이치", "4165": "주가조작", "4166": "낸셜", "4167": "매매", "4168": "특혜", "4169": "박탈", "4170": "골자", "4171": "폭제", "4172": "표류", "4173": "단서", "4174": "영장", "4175": "발부", "4176": "과세", "4177": "애초", "4178": "위법성", "4179": "부진", "4180": "면치", "4181": "친분", "4182": "윤우", "4183": "용산세무서", "4184": "뇌물수수", "4185": "진두", "4186": "제자리걸음", "4187": "프로포폴", "4188": "투약", "4189": "이용구", "4190": "만인", "4191": "당분간", "4192": "고위", "4193": "이첩", "4194": "겹", "4195": "도감", "4196": "전개", "4197": "장담", "4198": "단기간", "4199": "대검", "4200": "수장", "4201": "오해", "4202": "소지", "4203": "정준", "4204": "진급", "4205": "천안함", "4206": "계급", "4207": "추서", "4208": "연금", "4209": "지급", "4210": "국방부", "4211": "특별법", "4212": "예우", "4213": "항의", "4214": "일괄", "4215": "소급", "4216": "한기호", "4217": "전사", "4218": "순직", "4219": "일자", "4220": "폭침", "4221": "임재", "4222": "상사", "4223": "중사", "4224": "하사", "4225": "위인", "4226": "유가족", "4227": "예정자", "4228": "한해", "4229": "내외", "4230": "우도", "4231": "해군", "4232": "실무", "4233": "지침", "4234": "수정", "4235": "통지", "4236": "해명", "4237": "행태", "4238": "연평해전", "4239": "참수리", "4240": "정장", "4241": "윤영하", "4242": "소령", "4243": "대위", "4244": "의문", "4245": "김상진", "4246": "박용", "4247": "전신", "4248": "마비", "4249": "도비", "4250": "의향", "4251": "유튜브", "4252": "불안감", "4253": "조장", "4254": "아스", "4255": "트", "4256": "카", "4257": "부작용", "4258": "마포구", "4259": "족발", "4260": "김모", "4261": "자임", "4262": "혈전", "4263": "탓", "4264": "추진단", "4265": "대상자", "4266": "완료", "4267": "종로구", "4268": "탑골", "4269": "동묘", "4270": "구제", "4271": "구로구", "4272": "가리봉", "4273": "마포", "4274": "토로", "4275": "정모", "4276": "대도", "4277": "하필", "4278": "한숨", "4279": "이상은", "4280": "퍼뜨려", "4281": "지적도", "4282": "숨기", "4283": "일해", "4284": "항체", "4285": "성률", "4286": "노쇼", "4287": "은미", "4288": "호흡기", "4289": "돌파", "4290": "동의", "4291": "손지민", "4292": "승곤", "4293": "멘붕", "4294": "존버", "4295": "도박", "4296": "가까스로", "4297": "황판", "4298": "커서", "4299": "전전긍긍", "4300": "위험성", "4301": "수업료", "4302": "등락", "4303": "사이다", "4304": "사별", "4305": "흥국", "4306": "유진", "4307": "비관", "4308": "노벨경제학상", "4309": "수상자", "4310": "크루그먼", "4311": "뉴욕시립대", "4312": "기고", "4313": "출시", "4314": "돈세탁", "4315": "해커", "4316": "효용", "4317": "급등", "4318": "오름", "4319": "세로", "4320": "견해"}